README.md
setup.py
ws2801.py
micropython_ws2801.egg-info/PKG-INFO
micropython_ws2801.egg-info/SOURCES.txt
micropython_ws2801.egg-info/dependency_links.txt
micropython_ws2801.egg-info/top_level.txt